{"is_source_file": false, "format": "", "description": "", "external_files": [], "external_methods": [], "published": [], "classes": [], "methods": [], "calls": [], "search-terms": ["gradle.properties", "build speed", "androidX", "kotlin.incremental", "gradle daemon"], "state": 2, "file_id": 13, "knowledge_revision": 45, "git_revision": "75b651b24834fb2aa9fc115041480586fa7c1943", "hash": "80005a945b03fabd3c6b19a6f8d9f347", "format-version": 4, "code-base-name": "mobile_frontend", "filename": "mobile_frontend/android/gradle.properties", "revision_history": [{"45": "75b651b24834fb2aa9fc115041480586fa7c1943"}]}